deepctl_cmd_usage/__init__.py
deepctl_cmd_usage/command.py
deepctl_cmd_usage/models.py
deepctl_cmd_usage-0.1.10.dist-info/METADATA
deepctl_cmd_usage-0.1.10.dist-info/WHEEL
deepctl_cmd_usage-0.1.10.dist-info/entry_points.txt
deepctl_cmd_usage-0.1.10.dist-info/top_level.txt
deepctl_cmd_usage-0.1.10.dist-info/RECORD
